mpe2/__init__.py
mpe2/all_modules.py
mpe2/simple_adversary_v3.py
mpe2/simple_crypto_v3.py
mpe2/simple_push_v3.py
mpe2/simple_reference_v3.py
mpe2/simple_speaker_listener_v4.py
mpe2/simple_spread_v3.py
mpe2/simple_tag_v3.py
mpe2/simple_v3.py
mpe2/simple_world_comm_v3.py
mpe2/_mpe_utils/__init__.py
mpe2/_mpe_utils/core.py
mpe2/_mpe_utils/scenario.py
mpe2/_mpe_utils/secrcode.ttf
mpe2/_mpe_utils/simple_env.py
mpe2/simple/simple.py
mpe2/simple_adversary/simple_adversary.py
mpe2/simple_crypto/simple_crypto.py
mpe2/simple_push/simple_push.py
mpe2/simple_reference/simple_reference.py
mpe2/simple_speaker_listener/simple_speaker_listener.py
mpe2/simple_spread/simple_spread.py
mpe2/simple_tag/simple_tag.py
mpe2/simple_world_comm/simple_world_comm.py
mpe2-0.0.1.dist-info/LICENSE
mpe2-0.0.1.dist-info/METADATA
mpe2-0.0.1.dist-info/WHEEL
mpe2-0.0.1.dist-info/top_level.txt
mpe2-0.0.1.dist-info/RECORD
