Metadata-Version: 2.1
Name: mpe2
Version: 0.0.1
Summary: Multi Particle Environments Version 2
Author-email: Farama Foundation <contact@farama.org>
License: MIT License
Keywords: Reinforcement Learning,game,RL,AI,gymnasium
Classifier: Development Status :: 1 - Planning
Classifier: License :: OSI Approved :: MIT License
Classifier: Programming Language :: Python :: 3
Classifier: Programming Language :: Python :: 3.10
Classifier: Intended Audience :: Science/Research
Classifier: Topic :: Scientific/Engineering :: Artificial Intelligence
Requires-Python: >=3.8
License-File: LICENSE
Requires-Dist: pettingzoo>=1.24.3
Requires-Dist: pygame>=2.6.0
Provides-Extra: testing
Requires-Dist: pynput==1.7.6; extra == "testing"
Requires-Dist: pytest==8.0.0; extra == "testing"
Requires-Dist: pytest-cov==4.1.0; extra == "testing"
Requires-Dist: pytest-xdist==3.5.0; extra == "testing"
Requires-Dist: pre-commit==3.5.0; extra == "testing"
Requires-Dist: pytest-markdown-docs==0.5.0; extra == "testing"
